chromoformer/__init__.py
chromoformer/data.py
chromoformer/modules.py
chromoformer/net.py
chromoformer/train.py
chromoformer/util.py
chromoformer-1.1.3.dist-info/LICENSE
chromoformer-1.1.3.dist-info/METADATA
chromoformer-1.1.3.dist-info/WHEEL
chromoformer-1.1.3.dist-info/top_level.txt
chromoformer-1.1.3.dist-info/RECORD
