Metadata-Version: 2.1
Name: chromoformer
Version: 1.1.3
Summary: Chromoformer - Pytorch
Home-page: https://github.com/dohlee/chromoformer
Author: Dohoon Lee
Author-email: dohlee.bioinfo@gmail.com
License: MIT
Keywords: artificial intelligence,epigenomics,gene expression prediction
Classifier: Development Status :: 4 - Beta
Classifier: Intended Audience :: Developers
Classifier: Topic :: Scientific/Engineering :: Artificial Intelligence
Classifier: License :: OSI Approved :: MIT License
Classifier: Programming Language :: Python :: 3.9
License-File: LICENSE
Requires-Dist: einops >=0.3
Requires-Dist: numpy
Requires-Dist: torch >=1.6
